isd_s3/__init__.py
isd_s3/__main__.py
isd_s3/config.py
isd_s3/isd_s3.py
isd_s3/test.test
isd_s3-1.1.0.dist-info/LICENSE
isd_s3-1.1.0.dist-info/METADATA
isd_s3-1.1.0.dist-info/WHEEL
isd_s3-1.1.0.dist-info/RECORD
