Metadata-Version: 2.1
Name: isd-s3
Version: 1.1.0
Summary: 
License: LICENSE
Author: Riley Conroy
Author-email: rpconroy@ucar.edu
Requires-Python: >=3.8,<4.0
Classifier: License :: Other/Proprietary License
Classifier: Programming Language :: Python :: 3
Classifier: Programming Language :: Python :: 3.8
Classifier: Programming Language :: Python :: 3.9
Classifier: Programming Language :: Python :: 3.10
Classifier: Programming Language :: Python :: 3.11
Classifier: Programming Language :: Python :: 3.12
Requires-Dist: boto3 (>=1.28.80,<2.0.0)
